pyeebls/pyeebls.pyf
pyeebls/__init__.py
pyeebls/eebls.f
pyeebls/_pyeebls.cpython-310-darwin.so
pyeebls/.dylibs/libgfortran.5.dylib
pyeebls/.dylibs/libquadmath.0.dylib
pyeebls/.dylibs/libgcc_s.1.1.dylib
pyeebls-0.2.0.dist-info/RECORD
pyeebls-0.2.0.dist-info/WHEEL
pyeebls-0.2.0.dist-info/METADATA
pyeebls-0.2.0.dist-info/licenses/LICENSE
