Metadata-Version: 2.2
Name: pyeebls
Version: 0.2.0
Summary: Python f2py extension wrapping eebls.f by Kovacs et al. 2002.
Keywords: astronomy,period-finding,fortran
Author-Email: Waqas Bhatti <waqas.afzal.bhatti@gmail.com>
License: MIT License
Classifier: Development Status :: 5 - Production/Stable
Classifier: License :: OSI Approved :: MIT License
Classifier: Intended Audience :: Science/Research
Classifier: Operating System :: OS Independent
Classifier: Programming Language :: Python :: 3 :: Only
Project-URL: Homepage, https://github.com/waqasbhatti/pyeebls
Project-URL: Documentation, https://github.com/waqasbhatti/pyeebls
Project-URL: Bug Tracker, https://github.com/waqasbhatti/pyeebls/issues
Requires-Python: >=3.8
Requires-Dist: numpy<2
